testdino-1.0.24.dist-info/licenses/LICENSE
testdino_cli/__init__.py
testdino_cli/version.py
testdino_cli/cli/__init__.py
testdino_cli/cli/commands.py
testdino_cli/cli/index.py
testdino_cli/cli/commands/__init__.py
testdino_cli/cli/commands/cache.py
testdino_cli/cli/commands/last_failed.py
testdino_cli/cli/commands/upload.py
testdino_cli/collectors/__init__.py
testdino_cli/collectors/ci.py
testdino_cli/collectors/git.py
testdino_cli/collectors/system.py
testdino_cli/config/__init__.py
testdino_cli/config/index.py
testdino_cli/core/__init__.py
testdino_cli/core/attachments.py
testdino_cli/core/build_detector.py
testdino_cli/core/cache_extractor.py
testdino_cli/core/discovery.py
testdino_cli/core/parser.py
testdino_cli/core/shard_detection.py
testdino_cli/core/validators.py
testdino_cli/services/__init__.py
testdino_cli/services/api.py
testdino_cli/services/azure.py
testdino_cli/services/cache_api.py
testdino_cli/services/sas.py
testdino_cli/services/upload.py
testdino_cli/types/__init__.py
testdino_cli/utils/__init__.py
testdino_cli/utils/env.py
testdino_cli/utils/files.py
testdino_cli/utils/fs.py
testdino_cli/utils/progress.py
testdino_cli/utils/retry.py
testdino_cli/utils/validation.py
testdino_cli/utils/verbose.py
testdino-1.0.24.dist-info/METADATA
testdino-1.0.24.dist-info/WHEEL
testdino-1.0.24.dist-info/entry_points.txt
testdino-1.0.24.dist-info/top_level.txt
testdino-1.0.24.dist-info/RECORD
