Metadata-Version: 2.4
Name: testdino
Version: 1.0.24
Summary: CLI tool for uploading Playwright test reports to TestDino platform with TestDino storage support
Author-email: TestDino Team <support@testdino.com>
License: MIT
Project-URL: Homepage, https://github.com/testdino-hq/testdino-py-cli#readme
Project-URL: Repository, https://github.com/testdino-hq/testdino-py-cli
Project-URL: Issues, https://github.com/testdino-hq/testdino-py-cli/issues
Keywords: playwright,testing,ci-cd,test-reports,testdino,storage,cli,python
Classifier: Development Status :: 4 - Beta
Classifier: Intended Audience :: Developers
Classifier: License :: OSI Approved :: MIT License
Classifier: Programming Language :: Python :: 3
Classifier: Programming Language :: Python :: 3.9
Classifier: Programming Language :: Python :: 3.10
Classifier: Programming Language :: Python :: 3.11
Classifier: Programming Language :: Python :: 3.12
Classifier: Topic :: Software Development :: Testing
Classifier: Topic :: Software Development :: Quality Assurance
Requires-Python: >=3.9
License-File: LICENSE
Requires-Dist: click>=8.1.0
Requires-Dist: pydantic>=2.0.0
Requires-Dist: python-dotenv>=1.0.0
Requires-Dist: gitpython>=3.1.0
Requires-Dist: httpx>=0.27.0
Requires-Dist: rich>=13.0.0
Requires-Dist: psutil>=5.9.0
Provides-Extra: dev
Requires-Dist: pytest>=8.0.0; extra == "dev"
Requires-Dist: pytest-asyncio>=0.23.0; extra == "dev"
Requires-Dist: black>=24.0.0; extra == "dev"
Requires-Dist: ruff>=0.3.0; extra == "dev"
Requires-Dist: mypy>=1.9.0; extra == "dev"
Dynamic: license-file
